healthcheck_helper/__init__.py
healthcheck_helper/healthcheck.ini
healthcheck_helper/main.py
healthcheck_helper/lib/__init__.py
healthcheck_helper/lib/service.py
healthcheck_helper-0.1.3.dist-info/METADATA
healthcheck_helper-0.1.3.dist-info/WHEEL
healthcheck_helper-0.1.3.dist-info/entry_points.txt
healthcheck_helper-0.1.3.dist-info/top_level.txt
healthcheck_helper-0.1.3.dist-info/RECORD
