Metadata-Version: 2.1
Name: healthcheck-helper
Version: 0.1.3
Author: M. Hakim Adiprasetya
Author-email: m.hakim.adiprasetya@gmail.com
Requires-Dist: fastapi
Requires-Dist: uvicorn
Requires-Dist: aiohttp
Requires-Dist: typer
Provides-Extra: tests
Requires-Dist: pytest ; extra == 'tests'
Requires-Dist: pytest-mock ; extra == 'tests'
Requires-Dist: pytest-asyncio ; extra == 'tests'
